s3sync/__init__.py
s3sync/__main__.py
s3sync/cli.py
s3sync/config.py
s3sync/lock.py
s3sync/metadata.py
s3sync/s3sync.py
s3sync/utils.py
s3_remotely_sync-0.1.1.dist-info/LICENSE
s3_remotely_sync-0.1.1.dist-info/METADATA
s3_remotely_sync-0.1.1.dist-info/WHEEL
s3_remotely_sync-0.1.1.dist-info/entry_points.txt
s3_remotely_sync-0.1.1.dist-info/top_level.txt
s3_remotely_sync-0.1.1.dist-info/RECORD
