Metadata-Version: 2.2
Name: s3-remotely-sync
Version: 0.1.1
Summary: A tool for synchronizing files with S3-compatible storage
Home-page: https://github.com/GuanceCloud/s3-remotely-sync.git
Author: Guance
Author-email: hmlu06@gmail.com
Classifier: Development Status :: 3 - Alpha
Classifier: Intended Audience :: Developers
Classifier: License :: OSI Approved :: MIT License
Classifier: Operating System :: OS Independent
Classifier: Programming Language :: Python :: 3
Classifier: Programming Language :: Python :: 3.11
Requires-Python: >=3.11
License-File: LICENSE
Requires-Dist: boto3>=1.26.0
Requires-Dist: botocore>=1.29.0
Requires-Dist: tqdm>=4.65.0
Requires-Dist: rich>=13.0.0
Requires-Dist: pyyaml>=6.0.0
Dynamic: author
Dynamic: author-email
Dynamic: classifier
Dynamic: description
Dynamic: description-content-type
Dynamic: home-page
Dynamic: requires-dist
Dynamic: requires-python
Dynamic: summary
